LICENSE
README.md
lyycfg.py
setup.py
lyycfg.egg-info/PKG-INFO
lyycfg.egg-info/SOURCES.txt
lyycfg.egg-info/dependency_links.txt
lyycfg.egg-info/top_level.txt