Metadata-Version: 2.1
Name: lyycfg
Version: 1.2
Summary: calendar for  lyy
Author: lyy
Author-email: 
License: MIT
License-File: LICENSE
